card_cli-1.1.11.dist-info/DESCRIPTION.rst
card_cli-1.1.11.dist-info/METADATA
card_cli-1.1.11.dist-info/RECORD
card_cli-1.1.11.dist-info/WHEEL
card_cli-1.1.11.dist-info/entry_points.txt
card_cli-1.1.11.dist-info/metadata.json
card_cli-1.1.11.dist-info/top_level.txt
card_reader/__init__.py
