Metadata-Version: 2.0
Name: card-cli
Version: 1.1.11
Summary: card-cli is a command line utility for reading smartcards and magnetic stripe cards.
Home-page: https://github.com/WietseGielen/card-reader-cli
Author: Wietse Gielen
Author-email: giertz@inuits.eu
License: UNKNOWN
Platform: UNKNOWN
Classifier: Programming Language :: Python :: 3
Classifier: License :: OSI Approved :: MIT License
Classifier: Operating System :: OS Independent
Requires-Python: >=3.6
Requires-Dist: pyusb (==1.0.0b2)
